{
  "HOMELESS_ID": "3d5a58bf-116c-4313-b444-eed0c7adde26",
  "BIRTHDAY": "1997-02-08",
  "COMMENTS": [
        {
          "COMMENT_AVANTAR": "https://img95.699pic.com/xsj/08/wg/1v.jpg%21/fh/300",
          "COMMENT_TAG": "Training",
          "COMMENT_TIME": "2023-07-15 10:48:09",
          "COMMENT_USER": "Bentley",
          "COMMENT_ORG": "Delaware Healthcare Association"
        }
  ],
  "ENTER_DATE": "2024-03-07 10:48:09",
  "ENTER_USER": "SYSTEM",
  "IMAGE": "https://img95.699pic.com/xsj/08/wg/1v.jpg%21/fh/300",
  "JOIN_DATE": "2023-12-19",
  "NAME": "Jemma",
  "ORG4": true,
  "SERVICE1": true,
  "ORG_SERVICE": {
      "ORG4": {
          "ORG_NAME": "Delaware Healthcare Association",
          "SERVICE1": {
              "SERVICE_NAME": "Training",
              "START_DATE": "2024-03-04",
              "PROGRESS_DETAIL": [
                  {
                      "DESC": "Work on phase5",
                      "TIME": "2022-10-31 10:48:09"
                  }
                  ,
                  {
                      "DESC": "Work on phase1",
                      "TIME": "2022-11-14 10:48:09"
                  }
                  ,
                  {
                      "DESC": "Work on phase4",
                      "TIME": "2023-09-26 10:48:09"
                  }
                  ,
                  {
                      "DESC": "Work on phase1",
                      "TIME": "2023-10-16 10:48:09"
                  }
                  ,
                  {
                      "DESC": "Work on phase4",
                      "TIME": "2023-12-05 10:48:09"
                  }
              ],
              "END_DATE": "2024-01-06"
          }
      }
  },
  "PERMANENT_DATE": "",
  "PHONE": "13262918544",
  "REQUEST": "Need food",
  "STATUS": "PERMANENT"
}
